animdl2/__init__.py
animdl2/__main__.py
animdl2/core/__init__.py
animdl2/core/__version__.py
animdl2/core/cli/__init__.py
animdl2/core/cli/commands/__init__.py
animdl2/core/cli/commands/download.py
animdl2/core/cli/commands/grab.py
animdl2/core/cli/commands/schedule.py
animdl2/core/cli/commands/search.py
animdl2/core/cli/commands/stream.py
animdl2/core/cli/commands/update.py
animdl2/core/cli/exit_codes.py
animdl2/core/cli/helpers/__init__.py
animdl2/core/cli/helpers/aniskip.py
animdl2/core/cli/helpers/banner.py
animdl2/core/cli/helpers/constants.py
animdl2/core/cli/helpers/decorators.py
animdl2/core/cli/helpers/fuzzysearch.py
animdl2/core/cli/helpers/intelliq.py
animdl2/core/cli/helpers/logger.py
animdl2/core/cli/helpers/player.py
animdl2/core/cli/helpers/players/__init__.py
animdl2/core/cli/helpers/players/android.py
animdl2/core/cli/helpers/players/base_player.py
animdl2/core/cli/helpers/players/ffplay.py
animdl2/core/cli/helpers/players/mpv.py
animdl2/core/cli/helpers/players/vlc.py
animdl2/core/cli/helpers/processors.py
animdl2/core/cli/helpers/prompts.py
animdl2/core/cli/helpers/rpc.py
animdl2/core/cli/helpers/searcher.py
animdl2/core/cli/helpers/special.py
animdl2/core/cli/helpers/stream_handlers.py
animdl2/core/cli/http_client.py
animdl2/core/codebase/__init__.py
animdl2/core/codebase/downloader/__init__.py
animdl2/core/codebase/downloader/ffmpeg.py
animdl2/core/codebase/downloader/handle.py
animdl2/core/codebase/downloader/hls.py
animdl2/core/codebase/downloader/idmanlib.py
animdl2/core/codebase/extractors/__init__.py
animdl2/core/codebase/extractors/dailymotion/__init__.py
animdl2/core/codebase/extractors/doodstream/__init__.py
animdl2/core/codebase/extractors/gogoplay/__init__.py
animdl2/core/codebase/extractors/mp4upload/__init__.py
animdl2/core/codebase/extractors/mycloud/__init__.py
animdl2/core/codebase/extractors/okru/__init__.py
animdl2/core/codebase/extractors/rapidvideo/__init__.py
animdl2/core/codebase/extractors/rapidvideo/polling.py
animdl2-1.7.29.dist-info/entry_points.txt
animdl2-1.7.29.dist-info/LICENSE
animdl2-1.7.29.dist-info/METADATA
animdl2-1.7.29.dist-info/WHEEL
animdl2-1.7.29.dist-info/RECORD
