Metadata-Version: 2.1
Name: animdl2
Version: 1.7.29
Summary: A highly efficient, fast, powerful and light-weight anime downloader and streamer for your favorite anime.
License: GPL-3.0-only
Author: justfoolingaround
Author-email: kr.justfoolingaround@gmail.com
Requires-Python: >=3.7,<4.0
Classifier: License :: OSI Approved :: GNU General Public License v3 (GPLv3)
Classifier: Programming Language :: Python :: 3
Classifier: Programming Language :: Python :: 3.7
Classifier: Programming Language :: Python :: 3.8
Classifier: Programming Language :: Python :: 3.9
Classifier: Programming Language :: Python :: 3.10
Classifier: Programming Language :: Python :: 3.11
Classifier: Programming Language :: Python :: 3.12
Requires-Dist: anchor-kr (>=0.1.3,<0.2.0)
Requires-Dist: anitopy (>=2.1.0,<2.2.0)
Requires-Dist: click (>=8.0.4,<8.2.0)
Requires-Dist: comtypes (>=1.1.11,<1.2.0)
Requires-Dist: cssselect (>=1.1,<1.3)
Requires-Dist: httpx (>=0.23.0,<0.24.0)
Requires-Dist: lxml (==4.9.1) ; sys_platform != "win32"
Requires-Dist: packaging (>=22,<24)
Requires-Dist: pkginfo (>=1.9.2,<2.0.0)
Requires-Dist: pycryptodomex (>=3.14.1,<3.15.0)
Requires-Dist: pyyaml (>=6.0,<7.0)
Requires-Dist: regex (>=2022.10.31,<2022.11.0)
Requires-Dist: rich (>=13.3.1,<13.3.4)
Requires-Dist: tqdm (>=4.62.3,<4.66.0)
Requires-Dist: yarl (>=1.8.1,<1.9.0)
